astronomia/__init__.py
astronomia/astronomia.py
astronomia/astronomia_params.txt
astronomia/calendar.py
astronomia/commonterms.py
astronomia/constants.py
astronomia/coordinates.py
astronomia/dynamical.py
astronomia/equinox.py
astronomia/globals.py
astronomia/lunar.py
astronomia/nutation.py
astronomia/planets.py
astronomia/riseset.py
astronomia/sun.py
astronomia/util.py
astronomia/vsop87d_dict.py
astronomia/apps/check_perihelion.py
astronomia/apps/cronus.py
astronomia/apps/solstice.py
astronomia/cgi/easter_cgi.py
astronomia/cgi/solstice_cgi.py
astronomia/toolbox_utils/docs/conf.py
astronomia/toolbox_utils/src/toolbox_utils/__init__.py
astronomia/toolbox_utils/src/toolbox_utils/tsutils.py
astronomia/toolbox_utils/src/toolbox_utils/readers/__init__.py
astronomia/toolbox_utils/src/toolbox_utils/readers/hbn.py
astronomia/toolbox_utils/src/toolbox_utils/readers/plotgen.py
astronomia/toolbox_utils/src/toolbox_utils/readers/wdm.py
astronomia/toolbox_utils/tests/test_asbestfreq.py
astronomia/toolbox_utils/tests/test_date_slice.py
astronomia/toolbox_utils/tests/test_dateparse.py
astronomia/toolbox_utils/tests/test_extract.py
astronomia/toolbox_utils/tests/test_hbn.py
astronomia/toolbox_utils/tests/test_make_list.py
astronomia/toolbox_utils/tests/test_period_timestamp.py
astronomia/toolbox_utils/tests/test_plotgen.py
astronomia/toolbox_utils/tests/test_range_to_numlist.py
astronomia/toolbox_utils/tests/test_read.py
astronomia/toolbox_utils/tests/test_wdm.py
astronomia-3.0.2.dist-info/LICENSE.txt
astronomia-3.0.2.dist-info/METADATA
astronomia-3.0.2.dist-info/WHEEL
astronomia-3.0.2.dist-info/entry_points.txt
astronomia-3.0.2.dist-info/top_level.txt
astronomia-3.0.2.dist-info/RECORD
